laptop_detect/__init__.py
laptop_detect/laptop_detect.py
laptop_detect-0.0.1.dist-info/LICENSE
laptop_detect-0.0.1.dist-info/METADATA
laptop_detect-0.0.1.dist-info/WHEEL
laptop_detect-0.0.1.dist-info/top_level.txt
laptop_detect-0.0.1.dist-info/RECORD
