Metadata-Version: 2.1
Name: laptop-detect
Version: 0.0.1
Summary: A port of the popular laptop-detect shell script
Home-page: https://gitlab.com/thomasjlsn/laptop-detect-py
Author: Thomas Ellison
Author-email: thomasjlsn@gmail.com
License: UNKNOWN
Platform: UNKNOWN
Classifier: License :: OSI Approved :: GNU General Public License v3 (GPLv3)
Classifier: Programming Language :: Python :: 3
License-File: LICENSE
